parent.py
parent-25.2.dist-info/METADATA
parent-25.2.dist-info/WHEEL
parent-25.2.dist-info/entry_points.txt
parent-25.2.dist-info/licenses/LICENSE
parent-25.2.dist-info/RECORD
