Metadata-Version: 2.4
Name: parent
Version: 25.2
Summary: 
License: MIT
License-File: LICENSE
Author: Adam Zahradník
Author-email: adam@zahradnik.xyz
Requires-Python: >=3.11,<4.0
Classifier: License :: OSI Approved :: MIT License
Classifier: Programming Language :: Python :: 3
Classifier: Programming Language :: Python :: 3.11
Classifier: Programming Language :: Python :: 3.12
Classifier: Programming Language :: Python :: 3.13
Classifier: Programming Language :: Python :: 3.14
Requires-Dist: click (>=8.1.7,<9.0.0)
Requires-Dist: landlock (>=1.0.0.dev4,<2.0.0)
Requires-Dist: pyseccomp (>=0.1.2,<0.2.0)
Requires-Dist: python-prctl (>=1.8.1,<2.0.0)
